{"release_time": "2025-05-12T19:52:13+0800", "update_time": "2025-05-12T19:52:39+0800", "description": {"title": "CCTV6 节目单", "subtitle": null, "source": "https://tv.cctv.com/epg/index.shtml", "link": "https://api.cntv.cn/epg/getEpgInfoByChannelNew", "page_start": 1, "page_end": 1, "page_total": 1, "page_limit": -1, "item_total": 1, "item_limit": 1, "page_count": 1, "sup_page_count": 0}, "extra": {"channelName": "CCTV-6 电影", "lvUrl": "https://tv.cctv.com/live/cctv6"}, "stats": {"movies": 27}, "movies": [{"name": "滚蛋吧！肿瘤君", "ext": {"startTime": 1739981299, "endTime": 1739982008, "showTime": "00:08", "eventType": "", "eventId": "", "length": 709, "column_url": "", "columnBackvideourl": "", "top": ""}}, {"name": "中国体育彩票阳光开奖2025-02-19", "ext": {"startTime": 1739982008, "endTime": 1739982068, "showTime": "00:20", "eventType": "", "eventId": "", "length": 60, "column_url": "", "columnBackvideourl": "", "top": ""}}, {"name": "中国体育彩票阳光开奖2025-02-19", "ext": {"startTime": 1739982068, "endTime": 1739982253, "showTime": "00:21", "eventType": "", "eventId": "", "length": 185, "column_url": "", "columnBackvideourl": "", "top": ""}}, {"name": "今日影评2025-036", "ext": {"startTime": 1739982253, "endTime": 1739982313, "showTime": "00:24", "eventType": "", "eventId": "", "length": 60, "column_url": "", "columnBackvideourl": "", "top": ""}}, {"name": "今日影评2025-036", "ext": {"startTime": 1739982313, "endTime": 1739983123, "showTime": "00:25", "eventType": "", "eventId": "", "length": 810, "column_url": "", "columnBackvideourl": "", "top": ""}}, {"name": "滚蛋吧！肿瘤君", "ext": {"startTime": 1739983123, "endTime": 1739983183, "showTime": "00:38", "eventType": "", "eventId": "", "length": 60, "column_url": "", "columnBackvideourl": "", "top": ""}}, {"name": "滚蛋吧！肿瘤君", "ext": {"startTime": 1739983183, "endTime": 1739988185, "showTime": "00:39", "eventType": "", "eventId": "", "length": 5002, "column_url": "", "columnBackvideourl": "", "top": ""}}, {"name": "村学的冬天", "ext": {"startTime": 1739988185, "endTime": 1739990249, "showTime": "02:03", "eventType": "", "eventId": "", "length": 2064, "column_url": "", "columnBackvideourl": "", "top": ""}}, {"name": "村学的冬天", "ext": {"startTime": 1739990249, "endTime": 1739990623, "showTime": "02:37", "eventType": "", "eventId": "", "length": 374, "column_url": "", "columnBackvideourl": "", "top": ""}}, {"name": "村学的冬天", "ext": {"startTime": 1739990623, "endTime": 1739993547, "showTime": "02:43", "eventType": "", "eventId": "", "length": 2924, "column_url": "", "columnBackvideourl": "", "top": ""}}, {"name": "情归伊敏河", "ext": {"startTime": 1739993547, "endTime": 1739998424, "showTime": "03:32", "eventType": "", "eventId": "", "length": 4877, "column_url": "", "columnBackvideourl": "", "top": ""}}, {"name": "破风", "ext": {"startTime": 1739998424, "endTime": 1740005666, "showTime": "04:53", "eventType": "", "eventId": "", "length": 7242, "column_url": "", "columnBackvideourl": "", "top": ""}}, {"name": "刀尖", "ext": {"startTime": 1740005666, "endTime": 1740012949, "showTime": "06:54", "eventType": "", "eventId": "", "length": 7283, "column_url": "", "columnBackvideourl": "", "top": ""}}, {"name": "谁撞了我自己", "ext": {"startTime": 1740012949, "endTime": 1740019045, "showTime": "08:55", "eventType": "", "eventId": "", "length": 6096, "column_url": "", "columnBackvideourl": "", "top": ""}}, {"name": "女帅男兵", "ext": {"startTime": 1740019045, "endTime": 1740025159, "showTime": "10:37", "eventType": "", "eventId": "", "length": 6114, "column_url": "", "columnBackvideourl": "", "top": ""}}, {"name": "音乐电影欣赏", "ext": {"startTime": 1740025159, "endTime": 1740025509, "showTime": "12:19", "eventType": "", "eventId": "", "length": 350, "column_url": "", "columnBackvideourl": "", "top": ""}}, {"name": "冰雪大围捕", "ext": {"startTime": 1740025509, "endTime": 1740031557, "showTime": "12:25", "eventType": "", "eventId": "", "length": 6048, "column_url": "", "columnBackvideourl": "", "top": ""}}, {"name": "孕期完全指导", "ext": {"startTime": 1740031557, "endTime": 1740038390, "showTime": "14:05", "eventType": "", "eventId": "", "length": 6833, "column_url": "", "columnBackvideourl": "", "top": ""}}, {"name": "无枪", "ext": {"startTime": 1740038390, "endTime": 1740044133, "showTime": "15:59", "eventType": "", "eventId": "", "length": 5743, "column_url": "", "columnBackvideourl": "", "top": ""}}, {"name": "我和我的父辈：少年行", "ext": {"startTime": 1740044133, "endTime": 1740046927, "showTime": "17:35", "eventType": "", "eventId": "", "length": 2794, "column_url": "", "columnBackvideourl": "", "top": ""}}, {"name": "今日影评2025-037", "ext": {"startTime": 1740046927, "endTime": 1740047512, "showTime": "18:22", "eventType": "", "eventId": "", "length": 585, "column_url": "", "columnBackvideourl": "", "top": ""}}, {"name": "倩女幽魂：人间情", "ext": {"startTime": 1740047512, "endTime": 1740053604, "showTime": "18:31", "eventType": "", "eventId": "", "length": 6092, "column_url": "", "columnBackvideourl": "", "top": ""}}, {"name": "陌路狂刀", "ext": {"startTime": 1740053604, "endTime": 1740060000, "showTime": "20:13", "eventType": "", "eventId": "", "length": 6396, "column_url": "", "columnBackvideourl": "", "top": ""}}, {"name": "中国电影报道2025-051", "ext": {"startTime": 1740060000, "endTime": 1740061305, "showTime": "22:00", "eventType": "", "eventId": "", "length": 1305, "column_url": "", "columnBackvideourl": "", "top": ""}}, {"name": "王中王（上）", "ext": {"startTime": 1740061305, "endTime": 1740063602, "showTime": "22:21", "eventType": "", "eventId": "", "length": 2297, "column_url": "", "columnBackvideourl": "", "top": ""}}, {"name": "中国体育彩票阳光开奖2025-02-20", "ext": {"startTime": 1740063602, "endTime": 1740063662, "showTime": "23:00", "eventType": "", "eventId": "", "length": 60, "column_url": "", "columnBackvideourl": "", "top": ""}}, {"name": "王中王（下）", "ext": {"startTime": 1740063662, "endTime": 1740067140, "showTime": "23:01", "eventType": "", "eventId": "", "length": 3478, "column_url": "", "columnBackvideourl": "", "top": ""}}]}