{"release_time": "2025-05-12T19:50:51+0800", "update_time": "2025-05-12T19:51:49+0800", "description": {"title": "CCTV6 节目单", "subtitle": null, "source": "https://tv.cctv.com/epg/index.shtml", "link": "https://api.cntv.cn/epg/getEpgInfoByChannelNew", "page_start": 1, "page_end": 1, "page_total": 1, "page_limit": -1, "item_total": 1, "item_limit": 1, "page_count": 1, "sup_page_count": 0}, "extra": {"channelName": "CCTV-6 电影", "lvUrl": "https://tv.cctv.com/live/cctv6"}, "stats": {"movies": 20}, "movies": [{"name": "无间归途", "ext": {"startTime": 1743871235, "endTime": 1743876738, "showTime": "00:40", "eventType": "", "eventId": "", "length": 5503, "column_url": "", "columnBackvideourl": "", "top": ""}}, {"name": "日常幻想指南", "ext": {"startTime": 1743876738, "endTime": 1743882280, "showTime": "02:12", "eventType": "", "eventId": "", "length": 5542, "column_url": "", "columnBackvideourl": "", "top": ""}}, {"name": "容基耶尔小姐", "ext": {"startTime": 1743882280, "endTime": 1743888517, "showTime": "03:44", "eventType": "", "eventId": "", "length": 6237, "column_url": "", "columnBackvideourl": "", "top": ""}}, {"name": "第二届电影类型短片创投季作品《喜劫良缘》", "ext": {"startTime": 1743888517, "endTime": 1743890284, "showTime": "05:28", "eventType": "", "eventId": "", "length": 1767, "column_url": "", "columnBackvideourl": "", "top": ""}}, {"name": "第二届电影类型短片创投季作品《艾米与超帅》", "ext": {"startTime": 1743890284, "endTime": 1743891711, "showTime": "05:58", "eventType": "", "eventId": "", "length": 1427, "column_url": "", "columnBackvideourl": "", "top": ""}}, {"name": "二杠三", "ext": {"startTime": 1743891711, "endTime": 1743897832, "showTime": "06:21", "eventType": "", "eventId": "", "length": 6121, "column_url": "", "columnBackvideourl": "", "top": ""}}, {"name": "小旋风柴进之丹书铁劵", "ext": {"startTime": 1743897832, "endTime": 1743903630, "showTime": "08:03", "eventType": "", "eventId": "", "length": 5798, "column_url": "", "columnBackvideourl": "", "top": ""}}, {"name": "小旋风柴进之逼上梁山", "ext": {"startTime": 1743903630, "endTime": 1743909585, "showTime": "09:40", "eventType": "", "eventId": "", "length": 5955, "column_url": "", "columnBackvideourl": "", "top": ""}}, {"name": "音乐电影欣赏", "ext": {"startTime": 1743909585, "endTime": 1743910090, "showTime": "11:19", "eventType": "", "eventId": "", "length": 505, "column_url": "", "columnBackvideourl": "", "top": ""}}, {"name": "小旋风柴进之传世宝藏", "ext": {"startTime": 1743910090, "endTime": 1743916163, "showTime": "11:28", "eventType": "", "eventId": "", "length": 6073, "column_url": "", "columnBackvideourl": "", "top": ""}}, {"name": "小旋风柴进之簪花请命", "ext": {"startTime": 1743916163, "endTime": 1743922153, "showTime": "13:09", "eventType": "", "eventId": "", "length": 5990, "column_url": "", "columnBackvideourl": "", "top": ""}}, {"name": "佳片有约周日版2025-014", "ext": {"startTime": 1743922153, "endTime": 1743923303, "showTime": "14:49", "eventType": "", "eventId": "", "length": 1150, "column_url": "", "columnBackvideourl": "", "top": ""}}, {"name": "蛛丝马迹（2021）（上）", "ext": {"startTime": 1743923303, "endTime": 1743924879, "showTime": "15:08", "eventType": "", "eventId": "", "length": 1576, "column_url": "", "columnBackvideourl": "", "top": ""}}, {"name": "蛛丝马迹（2021）（下）", "ext": {"startTime": 1743924879, "endTime": 1743931373, "showTime": "15:34", "eventType": "", "eventId": "", "length": 6494, "column_url": "", "columnBackvideourl": "", "top": ""}}, {"name": "无双", "ext": {"startTime": 1743931373, "endTime": 1743939603, "showTime": "17:22", "eventType": "", "eventId": "", "length": 8230, "column_url": "", "columnBackvideourl": "", "top": ""}}, {"name": "血战台儿庄", "ext": {"startTime": 1743939603, "endTime": 1743948000, "showTime": "19:40", "eventType": "", "eventId": "", "length": 8397, "column_url": "", "columnBackvideourl": "", "top": ""}}, {"name": "中国电影报道2025-096", "ext": {"startTime": 1743948000, "endTime": 1743949375, "showTime": "22:00", "eventType": "", "eventId": "", "length": 1375, "column_url": "", "columnBackvideourl": "", "top": ""}}, {"name": "教父（上）", "ext": {"startTime": 1743949375, "endTime": 1743951626, "showTime": "22:22", "eventType": "", "eventId": "", "length": 2251, "column_url": "", "columnBackvideourl": "", "top": ""}}, {"name": "中国体育彩票阳光开奖2025-04-06", "ext": {"startTime": 1743951626, "endTime": 1743951686, "showTime": "23:00", "eventType": "", "eventId": "", "length": 60, "column_url": "", "columnBackvideourl": "", "top": ""}}, {"name": "教父（下）", "ext": {"startTime": 1743951686, "endTime": 1743955140, "showTime": "23:01", "eventType": "", "eventId": "", "length": 3454, "column_url": "", "columnBackvideourl": "", "top": ""}}]}